pronounspageviewer/__init__.py
pronounspageviewer/__main__.py
pronounspageviewer-1.0.2.dist-info/LICENSE.txt
pronounspageviewer-1.0.2.dist-info/METADATA
pronounspageviewer-1.0.2.dist-info/WHEEL
pronounspageviewer-1.0.2.dist-info/entry_points.txt
pronounspageviewer-1.0.2.dist-info/top_level.txt
pronounspageviewer-1.0.2.dist-info/RECORD
