Metadata-Version: 2.1
Name: pronounspageviewer
Version: 1.0.2
Summary: View a Pronouns.page from its JSON file
Author: Joe Greaves
Project-URL: Homepage, https://github.com/Grvs44/Pronouns.page-Viewer
Classifier: Programming Language :: Python :: 3
Classifier: License :: OSI Approved :: BSD License
Classifier: Operating System :: OS Independent
Requires-Python: >=3.10
License-File: LICENSE.txt
